pydra/tasks/nireports/__init__.py
pydra/tasks/nireports/_post_release.py
pydra/tasks/nireports/_version.py
pydra/tasks/nireports/interfaces/__init__.py
pydra/tasks/nireports/interfaces/dmri/__init__.py
pydra/tasks/nireports/interfaces/dmri/dwi_heatmap.py
pydra/tasks/nireports/interfaces/dmri/tests/conftest.py
pydra/tasks/nireports/interfaces/dmri/tests/test_dwiheatmap.py
pydra/tasks/nireports/interfaces/fmri/__init__.py
pydra/tasks/nireports/interfaces/fmri/fmri_summary.py
pydra/tasks/nireports/interfaces/fmri/tests/conftest.py
pydra/tasks/nireports/interfaces/fmri/tests/test_fmrisummary.py
pydra/tasks/nireports/interfaces/mosaic/__init__.py
pydra/tasks/nireports/interfaces/mosaic/plot_contours.py
pydra/tasks/nireports/interfaces/mosaic/plot_mosaic.py
pydra/tasks/nireports/interfaces/mosaic/plot_spikes.py
pydra/tasks/nireports/interfaces/mosaic/tests/conftest.py
pydra/tasks/nireports/interfaces/mosaic/tests/test_plotcontours.py
pydra/tasks/nireports/interfaces/mosaic/tests/test_plotmosaic.py
pydra/tasks/nireports/interfaces/mosaic/tests/test_plotspikes.py
pydra/tasks/nireports/interfaces/nuisance/__init__.py
pydra/tasks/nireports/interfaces/nuisance/comp_cor_variance_plot.py
pydra/tasks/nireports/interfaces/nuisance/confounds_correlation_plot.py
pydra/tasks/nireports/interfaces/nuisance/tests/conftest.py
pydra/tasks/nireports/interfaces/nuisance/tests/test_compcorvarianceplot.py
pydra/tasks/nireports/interfaces/nuisance/tests/test_confoundscorrelationplot.py
pydra/tasks/nireports/interfaces/reporting/__init__.py
pydra/tasks/nireports/interfaces/reporting/base/__init__.py
pydra/tasks/nireports/interfaces/reporting/base/simple_before_after_rpt.py
pydra/tasks/nireports/interfaces/reporting/base/tests/conftest.py
pydra/tasks/nireports/interfaces/reporting/base/tests/test_simplebeforeafterrpt.py
pydra/tasks/nireports/nipype_ports/__init__.py
pydra/tasks/nireports/nipype_ports/utils/__init__.py
pydra/tasks/nireports/nipype_ports/utils/filemanip.py
pydra_nireports-0.1.1.dist-info/METADATA
pydra_nireports-0.1.1.dist-info/WHEEL
pydra_nireports-0.1.1.dist-info/licenses/AUTHORS
pydra_nireports-0.1.1.dist-info/licenses/LICENSE
pydra_nireports-0.1.1.dist-info/licenses/NOTICE
pydra_nireports-0.1.1.dist-info/RECORD
